MANIFEST.in
README.rst
setup.py
fuzzydict/__init__.py
fuzzydict/fuzzydict.py
fuzzydict.egg-info/PKG-INFO
fuzzydict.egg-info/SOURCES.txt
fuzzydict.egg-info/dependency_links.txt
fuzzydict.egg-info/top_level.txt
fuzzydict/tests/fuzzydict_tests.py