Metadata-Version: 1.0
Name: fuzzydict
Version: 0.0.1
Summary: FuzzyDict, an ambiguous dictionary
Home-page: https://github.com/shoz/fuzzydict
Author: Shoji Ihara
Author-email: shoji.ihara@gmail.com
License: MIT
Keywords: data structure dictionary fuzzy
Platform: UNKNOWN
Classifier: Development Status :: 1 - Planning
Classifier: Intended Audience :: Developers
Classifier: Intended Audience :: Science/Research
Classifier: License :: OSI Approved :: MIT License
